Workbook

Sheet About This Plugin
A1: Earnings Call Sentiment Analyzer — Plugin Guide
A3: ⚙️ Configure Your Scoring Weights
A4: Edit the 'Your Weight' column (blue cells). Weights must sum to 100%. The Composite column in All Scores updates automatically.
A5: Dimension | B5: Description | C5: Default Weight | D5: Your Weight ✏
A6: Mgmt Tone | B6: Confidence, ownership, and energy of management delivery. | C6: 0.2 | D6: 0.2
A7: Fwd Guidance | B7: Strength, specificity, and direction of forward-looking statements. | C7: 0.25 | D7: 0.25
A8: Risk Language | B8: Frequency and severity of hedging, uncertainty, and risk vocabulary. | C8: 0.15 | D8: 0.15
A9: Analyst Sent. | B9: Tone of analyst questions — supportive vs. skeptical vs. adversarial. | C9: 0.2 | D9: 0.2
A10: Fin. Health | B10: Language around revenue, margins, cash flow, and balance sheet. | C10: 0.1 | D10: 0.1
A11: Strat. Clarity | B11: Coherence, specificity, and consistency of the strategic narrative. | C11: 0.1 | D11: 0.1
A12: TOTAL | B12: Weights must sum to 100% | C12: =SUM(C6:C11) -> 1 | D12: =SUM(D6:D11) -> 1
A14: 📋 What Is This Plugin?
A15: The Earnings Call Sentiment Analyzer scores earnings call transcripts across six investor-relevant dimensions using a structured rubric. Each dimension is rated on a scale of –5 (very negative) to +5 (very positive), then combined into a weighted composite score. You can customize the dimension weights in the table above to reflect your own investment philosophy. Results are tracked per company over time so you can monitor sentiment drift, compare management credibility across tickers, and flag calls that warrant deeper due diligence.
A16: ❓ What Questions Does the Analyzer Ask?
A17: Which transcript(s) to analyze? | B17: Paste the earnings call transcript text directly into the chat or upload a document. Multiple transcripts can be shared at once for a side-by-side comparison.
A18: What company and quarter is this? | B18: Identified automatically from the transcript header, or by asking you if ambiguous. Used to tag the scorecard row with Ticker, Company, Quarter, and Call Date.
A19: How do you want to weight the dimensions? | B19: You can accept the default weights (Guidance 25%, Tone 20%, Analyst 20%, Risk 15%, Health 10%, Clarity 10%) or specify your own — e.g. 'weight forward guidance at 40% and reduce analyst sentiment to 10%'. Custom weights are used for that session's composite and can be saved in the 'Your Weight' column above.
A20: Compare to prior quarters? | B20: If historical scores exist in this workbook, the analyzer can surface quarter-over-quarter shifts in tone, guidance quality, and analyst skepticism.
A21: Should I add this to the scorecard? | B21: After analysis you choose whether to append the scores to the All Scores tab. Company Summary averages update when new rows are added.
A22: ⚠️ Limitations & Important Notes
A23: Manual transcript sourcing | B23: Transcripts must currently be sourced and pasted manually — there is no live feed or automatic retrieval. This means the dataset only covers quarters for which you have provided transcripts, which may result in a shorter data history than ideal. Trend signals become more reliable as more quarters are added.
A24: Scoring is language-based, not financial | B24: Scores reflect tone and language from the call, not actual financial results. A company can score highly on management tone while missing consensus estimates. Always cross-reference with underlying financial data.
A25: Weight changes update composite formulas retroactively | B25: Changing 'Your Weight' cells above will recalculate all historical composite scores in All Scores automatically. This is intentional — so the workbook always reflects your current weighting philosophy. If you want to preserve a prior composite, copy-paste the column as values before changing weights.
A26: Subjectivity in borderline cases | B26: The rubric provides clear anchors, but calls near the boundary of two score levels involve some interpretive judgment. Scores should be used directionally, not as precise measurements.
A27: Analyst Sentiment requires Q&A | B27: If a transcript contains only prepared remarks, Analyst Sentiment is scored N/A and excluded from the composite. Adjust weights manually if Q&A is consistently absent for a company.
A28: Scoring scale: –5 = Very Negative | –3 = Negative | 0 = Neutral | +3 = Positive | +5 = Very Positive | Blue cells = user input

Sheet Company Summary
A1: Company Summary — Average Sentiment Scores Across All Quarters
A2: Ticker | B2: Company | C2: # Quarters | D2: Avg Mgmt Tone (×20%) | E2: Avg Fwd Guidance (×25%) | F2: Avg Risk Language (×15%) | G2: Avg Analyst Sent. (×20%) | H2: Avg Fin. Health (×10%) | I2: Avg Strat. Clarity (×10%) | J2: Avg Composite | K2: Trend (latest − first)
A3: AAPL | B3: Apple Inc. | C3: =COUNTIF('All Scores'!$A$3:$A$51,$A3) -> 5 | D3: =ROUND(AVERAGEIFS('All Scores'!$E$3:$E$51,'All Scores'!$A$3:$A$51,$A3),2) -> 2.8 | E3: =ROUND(AVERAGEIFS('All Scores'!$F$3:$F$51,'All Scores'!$A$3:$A$51,$A3),2) -> 2 | F3: =ROUND(AVERAGEIFS('All Scores'!$G$3:$G$51,'All Scores'!$A$3:$A$51,$A3),2) -> 0.8 | G3: =ROUND(AVERAGEIFS('All Scores'!$H$3:$H$51,'All Scores'!$A$3:$A$51,$A3),2) -> 1.8 | H3: =ROUND(AVERAGEIFS('All Scores'!$I$3:$I$51,'All Scores'!$A$3:$A$51,$A3),2) -> 2 | I3: =ROUND(AVERAGEIFS('All Scores'!$J$3:$J$51,'All Scores'!$A$3:$A$51,$A3),2) -> 1 | J3: =ROUND(AVERAGEIFS('All Scores'!$K$3:$K$51,'All Scores'!$A$3:$A$51,$A3),2) -> 1.84 | K3: =ROUND(INDEX('All Scores'!$K$3:$K$51,MATCH($A3,'All Scores'!$A$3:$A$51,0)+COUNTIF('All Scores'!$A$3:$A$51,$A3)-1)-INDEX('All Scores'!$K$3:$K$51,MATCH($A3,'All Scores'!$A$3:$A$51,0)),2) -> 2.35
A4: AMD | B4: Advanced Micro Devices | C4: =COUNTIF('All Scores'!$A$3:$A$51,$A4) -> 5 | D4: =ROUND(AVERAGEIFS('All Scores'!$E$3:$E$51,'All Scores'!$A$3:$A$51,$A4),2) -> 4 | E4: =ROUND(AVERAGEIFS('All Scores'!$F$3:$F$51,'All Scores'!$A$3:$A$51,$A4),2) -> 3.8 | F4: =ROUND(AVERAGEIFS('All Scores'!$G$3:$G$51,'All Scores'!$A$3:$A$51,$A4),2) -> 1.8 | G4: =ROUND(AVERAGEIFS('All Scores'!$H$3:$H$51,'All Scores'!$A$3:$A$51,$A4),2) -> 2.8 | H4: =ROUND(AVERAGEIFS('All Scores'!$I$3:$I$51,'All Scores'!$A$3:$A$51,$A4),2) -> 4 | I4: =ROUND(AVERAGEIFS('All Scores'!$J$3:$J$51,'All Scores'!$A$3:$A$51,$A4),2) -> 3 | J4: =ROUND(AVERAGEIFS('All Scores'!$K$3:$K$51,'All Scores'!$A$3:$A$51,$A4),2) -> 3.28 | K4: =ROUND(INDEX('All Scores'!$K$3:$K$51,MATCH($A4,'All Scores'!$A$3:$A$51,0)+COUNTIF('All Scores'!$A$3:$A$51,$A4)-1)-INDEX('All Scores'!$K$3:$K$51,MATCH($A4,'All Scores'!$A$3:$A$51,0)),2) -> 0.35
A5: CAT | B5: Caterpillar Inc. | C5: =COUNTIF('All Scores'!$A$3:$A$51,$A5) -> 5 | D5: =ROUND(AVERAGEIFS('All Scores'!$E$3:$E$51,'All Scores'!$A$3:$A$51,$A5),2) -> 3.4 | E5: =ROUND(AVERAGEIFS('All Scores'!$F$3:$F$51,'All Scores'!$A$3:$A$51,$A5),2) -> 4 | F5: =ROUND(AVERAGEIFS('All Scores'!$G$3:$G$51,'All Scores'!$A$3:$A$51,$A5),2) -> 0 | G5: =ROUND(AVERAGEIFS('All Scores'!$H$3:$H$51,'All Scores'!$A$3:$A$51,$A5),2) -> -2 | H5: =ROUND(AVERAGEIFS('All Scores'!$I$3:$I$51,'All Scores'!$A$3:$A$51,$A5),2) -> 2.6 | I5: =ROUND(AVERAGEIFS('All Scores'!$J$3:$J$51,'All Scores'!$A$3:$A$51,$A5),2) -> 3.8 | J5: =ROUND(AVERAGEIFS('All Scores'!$K$3:$K$51,'All Scores'!$A$3:$A$51,$A5),2) -> 1.92 | K5: =ROUND(INDEX('All Scores'!$K$3:$K$51,MATCH($A5,'All Scores'!$A$3:$A$51,0)+COUNTIF('All Scores'!$A$3:$A$51,$A5)-1)-INDEX('All Scores'!$K$3:$K$51,MATCH($A5,'All Scores'!$A$3:$A$51,0)),2) -> 1.4
A6: CVX | B6: Chevron Corporation | C6: =COUNTIF('All Scores'!$A$3:$A$51,$A6) -> 5 | D6: =ROUND(AVERAGEIFS('All Scores'!$E$3:$E$51,'All Scores'!$A$3:$A$51,$A6),2) -> 3.6 | E6: =ROUND(AVERAGEIFS('All Scores'!$F$3:$F$51,'All Scores'!$A$3:$A$51,$A6),2) -> 3.4 | F6: =ROUND(AVERAGEIFS('All Scores'!$G$3:$G$51,'All Scores'!$A$3:$A$51,$A6),2) -> 1.6 | G6: =ROUND(AVERAGEIFS('All Scores'!$H$3:$H$51,'All Scores'!$A$3:$A$51,$A6),2) -> -0.8 | H6: =ROUND(AVERAGEIFS('All Scores'!$I$3:$I$51,'All Scores'!$A$3:$A$51,$A6),2) -> 4 | I6: =ROUND(AVERAGEIFS('All Scores'!$J$3:$J$51,'All Scores'!$A$3:$A$51,$A6),2) -> 2.6 | J6: =ROUND(AVERAGEIFS('All Scores'!$K$3:$K$51,'All Scores'!$A$3:$A$51,$A6),2) -> 2.31 | K6: =ROUND(INDEX('All Scores'!$K$3:$K$51,MATCH($A6,'All Scores'!$A$3:$A$51,0)+COUNTIF('All Scores'!$A$3:$A$51,$A6)-1)-INDEX('All Scores'!$K$3:$K$51,MATCH($A6,'All Scores'!$A$3:$A$51,0)),2) -> -0.2
A7: GOOG | B7: Alphabet Inc. | C7: =COUNTIF('All Scores'!$A$3:$A$51,$A7) -> 4 | D7: =ROUND(AVERAGEIFS('All Scores'!$E$3:$E$51,'All Scores'!$A$3:$A$51,$A7),2) -> 3 | E7: =ROUND(AVERAGEIFS('All Scores'!$F$3:$F$51,'All Scores'!$A$3:$A$51,$A7),2) -> 1.25 | F7: =ROUND(AVERAGEIFS('All Scores'!$G$3:$G$51,'All Scores'!$A$3:$A$51,$A7),2) -> -1 | G7: =ROUND(AVERAGEIFS('All Scores'!$H$3:$H$51,'All Scores'!$A$3:$A$51,$A7),2) -> 2 | H7: =ROUND(AVERAGEIFS('All Scores'!$I$3:$I$51,'All Scores'!$A$3:$A$51,$A7),2) -> 3.25 | I7: =ROUND(AVERAGEIFS('All Scores'!$J$3:$J$51,'All Scores'!$A$3:$A$51,$A7),2) -> 3 | J7: =ROUND(AVERAGEIFS('All Scores'!$K$3:$K$51,'All Scores'!$A$3:$A$51,$A7),2) -> 1.79 | K7: =ROUND(INDEX('All Scores'!$K$3:$K$51,MATCH($A7,'All Scores'!$A$3:$A$51,0)+COUNTIF('All Scores'!$A$3:$A$51,$A7)-1)-INDEX('All Scores'!$K$3:$K$51,MATCH($A7,'All Scores'!$A$3:$A$51,0)),2) -> 0.2
A8: HD | B8: The Home Depot | C8: =COUNTIF('All Scores'!$A$3:$A$51,$A8) -> 5 | D8: =ROUND(AVERAGEIFS('All Scores'!$E$3:$E$51,'All Scores'!$A$3:$A$51,$A8),2) -> 2.2 | E8: =ROUND(AVERAGEIFS('All Scores'!$F$3:$F$51,'All Scores'!$A$3:$A$51,$A8),2) -> 0 | F8: =ROUND(AVERAGEIFS('All Scores'!$G$3:$G$51,'All Scores'!$A$3:$A$51,$A8),2) -> -2 | G8: =ROUND(AVERAGEIFS('All Scores'!$H$3:$H$51,'All Scores'!$A$3:$A$51,$A8),2) -> 0.2 | H8: =ROUND(AVERAGEIFS('All Scores'!$I$3:$I$51,'All Scores'!$A$3:$A$51,$A8),2) -> 2.2 | I8: =ROUND(AVERAGEIFS('All Scores'!$J$3:$J$51,'All Scores'!$A$3:$A$51,$A8),2) -> 1.4 | J8: =ROUND(AVERAGEIFS('All Scores'!$K$3:$K$51,'All Scores'!$A$3:$A$51,$A8),2) -> 0.54 | K8: =ROUND(INDEX('All Scores'!$K$3:$K$51,MATCH($A8,'All Scores'!$A$3:$A$51,0)+COUNTIF('All Scores'!$A$3:$A$51,$A8)-1)-INDEX('All Scores'!$K$3:$K$51,MATCH($A8,'All Scores'!$A$3:$A$51,0)),2) -> -0.65
A9: MCD | B9: McDonald's Corporation | C9: =COUNTIF('All Scores'!$A$3:$A$51,$A9) -> 5 | D9: =ROUND(AVERAGEIFS('All Scores'!$E$3:$E$51,'All Scores'!$A$3:$A$51,$A9),2) -> 3.8 | E9: =ROUND(AVERAGEIFS('All Scores'!$F$3:$F$51,'All Scores'!$A$3:$A$51,$A9),2) -> 4 | F9: =ROUND(AVERAGEIFS('All Scores'!$G$3:$G$51,'All Scores'!$A$3:$A$51,$A9),2) -> -3.2 | G9: =ROUND(AVERAGEIFS('All Scores'!$H$3:$H$51,'All Scores'!$A$3:$A$51,$A9),2) -> -2.4 | H9: =ROUND(AVERAGEIFS('All Scores'!$I$3:$I$51,'All Scores'!$A$3:$A$51,$A9),2) -> 4 | I9: =ROUND(AVERAGEIFS('All Scores'!$J$3:$J$51,'All Scores'!$A$3:$A$51,$A9),2) -> 4 | J9: =ROUND(AVERAGEIFS('All Scores'!$K$3:$K$51,'All Scores'!$A$3:$A$51,$A9),2) -> 1.6 | K9: =ROUND(INDEX('All Scores'!$K$3:$K$51,MATCH($A9,'All Scores'!$A$3:$A$51,0)+COUNTIF('All Scores'!$A$3:$A$51,$A9)-1)-INDEX('All Scores'!$K$3:$K$51,MATCH($A9,'All Scores'!$A$3:$A$51,0)),2) -> 0.15
A10: PFE | B10: Pfizer Inc. | C10: =COUNTIF('All Scores'!$A$3:$A$51,$A10) -> 5 | D10: =ROUND(AVERAGEIFS('All Scores'!$E$3:$E$51,'All Scores'!$A$3:$A$51,$A10),2) -> 4 | E10: =ROUND(AVERAGEIFS('All Scores'!$F$3:$F$51,'All Scores'!$A$3:$A$51,$A10),2) -> 4 | F10: =ROUND(AVERAGEIFS('All Scores'!$G$3:$G$51,'All Scores'!$A$3:$A$51,$A10),2) -> -2.4 | G10: =ROUND(AVERAGEIFS('All Scores'!$H$3:$H$51,'All Scores'!$A$3:$A$51,$A10),2) -> -1.4 | H10: =ROUND(AVERAGEIFS('All Scores'!$I$3:$I$51,'All Scores'!$A$3:$A$51,$A10),2) -> 4 | I10: =ROUND(AVERAGEIFS('All Scores'!$J$3:$J$51,'All Scores'!$A$3:$A$51,$A10),2) -> 4 | J10: =ROUND(AVERAGEIFS('All Scores'!$K$3:$K$51,'All Scores'!$A$3:$A$51,$A10),2) -> 1.96 | K10: =ROUND(INDEX('All Scores'!$K$3:$K$51,MATCH($A10,'All Scores'!$A$3:$A$51,0)+COUNTIF('All Scores'!$A$3:$A$51,$A10)-1)-INDEX('All Scores'!$K$3:$K$51,MATCH($A10,'All Scores'!$A$3:$A$51,0)),2) -> 0
A11: UNH | B11: UnitedHealth Group | C11: =COUNTIF('All Scores'!$A$3:$A$51,$A11) -> 5 | D11: =ROUND(AVERAGEIFS('All Scores'!$E$3:$E$51,'All Scores'!$A$3:$A$51,$A11),2) -> 2.6 | E11: =ROUND(AVERAGEIFS('All Scores'!$F$3:$F$51,'All Scores'!$A$3:$A$51,$A11),2) -> 2.6 | F11: =ROUND(AVERAGEIFS('All Scores'!$G$3:$G$51,'All Scores'!$A$3:$A$51,$A11),2) -> 2 | G11: =ROUND(AVERAGEIFS('All Scores'!$H$3:$H$51,'All Scores'!$A$3:$A$51,$A11),2) -> 3.8 | H11: =ROUND(AVERAGEIFS('All Scores'!$I$3:$I$51,'All Scores'!$A$3:$A$51,$A11),2) -> 1 | I11: =ROUND(AVERAGEIFS('All Scores'!$J$3:$J$51,'All Scores'!$A$3:$A$51,$A11),2) -> 2.8 | J11: =ROUND(AVERAGEIFS('All Scores'!$K$3:$K$51,'All Scores'!$A$3:$A$51,$A11),2) -> 2.61 | K11: =ROUND(INDEX('All Scores'!$K$3:$K$51,MATCH($A11,'All Scores'!$A$3:$A$51,0)+COUNTIF('All Scores'!$A$3:$A$51,$A11)-1)-INDEX('All Scores'!$K$3:$K$51,MATCH($A11,'All Scores'!$A$3:$A$51,0)),2) -> -0.8
A12: WMT | B12: Walmart Inc. | C12: =COUNTIF('All Scores'!$A$3:$A$51,$A12) -> 5 | D12: =ROUND(AVERAGEIFS('All Scores'!$E$3:$E$51,'All Scores'!$A$3:$A$51,$A12),2) -> 3.8 | E12: =ROUND(AVERAGEIFS('All Scores'!$F$3:$F$51,'All Scores'!$A$3:$A$51,$A12),2) -> 3 | F12: =ROUND(AVERAGEIFS('All Scores'!$G$3:$G$51,'All Scores'!$A$3:$A$51,$A12),2) -> 3.6 | G12: =ROUND(AVERAGEIFS('All Scores'!$H$3:$H$51,'All Scores'!$A$3:$A$51,$A12),2) -> 4 | H12: =ROUND(AVERAGEIFS('All Scores'!$I$3:$I$51,'All Scores'!$A$3:$A$51,$A12),2) -> 3 | I12: =ROUND(AVERAGEIFS('All Scores'!$J$3:$J$51,'All Scores'!$A$3:$A$51,$A12),2) -> 3 | J12: =ROUND(AVERAGEIFS('All Scores'!$K$3:$K$51,'All Scores'!$A$3:$A$51,$A12),2) -> 3.45 | K12: =ROUND(INDEX('All Scores'!$K$3:$K$51,MATCH($A12,'All Scores'!$A$3:$A$51,0)+COUNTIF('All Scores'!$A$3:$A$51,$A12)-1)-INDEX('All Scores'!$K$3:$K$51,MATCH($A12,'All Scores'!$A$3:$A$51,0)),2) -> -0.1
A13: Score Legend: –5 = Very Negative | –3 = Negative | 0 = Neutral | +3 = Positive | +5 = Very Positive
A14: ≥ +3.0 Positive | B14: ≥ +1.0 Mild Positive | C14: ≥ –1.0 Neutral | D14: ≥ –3.0 Mild Negative

Sheet All Scores
A1: Earnings Call Sentiment Scorecard — All Transcripts
A2: Ticker | B2: Company | C2: Quarter | D2: Call Date | E2: Mgmt Tone (×Wt) | F2: Fwd Guidance (×Wt) | G2: Risk Language (×Wt) | H2: Analyst Sent. (×Wt) | I2: Fin. Health (×Wt) | J2: Strat. Clarity (×Wt) | K2: Composite * | L2: Notable Bullish Signal | M2: Notable Bearish Signal
A3: AAPL | B3: Apple Inc. | C3: Q4 FY2024 | D3: 10/31/2024 | E3: 2 | F3: 1 | G3: 0 | H3: 1 | I3: 1 | J3: 0 | K3: =ROUND('About This Plugin'!$D$6*E3+'About This Plugin'!$D$7*F3+'About This Plugin'!$D$8*G3+'About This Plugin'!$D$9*H3+'About This Plugin'!$D$10*I3+'About This Plugin'!$D$11*J3,2) -> 0.95 | L3: Stable Services growth and ecosystem momentum | M3: Flat forward guidance amid macro uncertainty
A4: AAPL | B4: Apple Inc. | C4: Q1 FY2025 | D4: 01/30/2025 | E4: 1 | F4: 0 | G4: -1 | H4: 0 | I4: 0 | J4: 0 | K4: =ROUND('About This Plugin'!$D$6*E4+'About This Plugin'!$D$7*F4+'About This Plugin'!$D$8*G4+'About This Plugin'!$D$9*H4+'About This Plugin'!$D$10*I4+'About This Plugin'!$D$11*J4,2) -> 0.05 | L4: Core Services segment remains resilient | M4: Tariff impacts, China demand weakness, guidance caution
A5: AAPL | B5: Apple Inc. | C5: Q2 FY2025 | D5: 05/01/2025 | E5: 3 | F5: 2 | G5: 1 | H5: 2 | I5: 2 | J5: 1 | K5: =ROUND('About This Plugin'!$D$6*E5+'About This Plugin'!$D$7*F5+'About This Plugin'!$D$8*G5+'About This Plugin'!$D$9*H5+'About This Plugin'!$D$10*I5+'About This Plugin'!$D$11*J5,2) -> 1.95 | L5: All-time revenue record; strong iPhone and Services growth | M5: Continuing tariff headwinds and China sensitivity
A6: AAPL | B6: Apple Inc. | C6: Q3 FY2025 | D6: 07/31/2025 | E6: 4 | F6: 3 | G6: 2 | H6: 3 | I6: 3 | J6: 2 | K6: =ROUND('About This Plugin'!$D$6*E6+'About This Plugin'!$D$7*F6+'About This Plugin'!$D$8*G6+'About This Plugin'!$D$9*H6+'About This Plugin'!$D$10*I6+'About This Plugin'!$D$11*J6,2) -> 2.95 | L6: Record EPS; AI product momentum; Services at all-time high | M6: Moderate supply chain complexity
A7: AAPL | B7: Apple Inc. | C7: Q4 FY2025 | D7: 10/30/2025 | E7: 4 | F7: 4 | G7: 2 | H7: 3 | I7: 4 | J7: 2 | K7: =ROUND('About This Plugin'!$D$6*E7+'About This Plugin'!$D$7*F7+'About This Plugin'!$D$8*G7+'About This Plugin'!$D$9*H7+'About This Plugin'!$D$10*I7+'About This Plugin'!$D$11*J7,2) -> 3.3 | L7: Record revenue across all categories; best quarter ever guidance | M7: Supply constraints on iPhone models
A8: AMD | B8: Advanced Micro Devices | C8: Q4 FY2024 | D8: 02/04/2025 | E8: 4 | F8: 3 | G8: 2 | H8: 3 | I8: 4 | J8: 3 | K8: =ROUND('About This Plugin'!$D$6*E8+'About This Plugin'!$D$7*F8+'About This Plugin'!$D$8*G8+'About This Plugin'!$D$9*H8+'About This Plugin'!$D$10*I8+'About This Plugin'!$D$11*J8,2) -> 3.15 | L8: Record financial metrics; strong AI momentum; clear product roadmap | M8: Gaming and Embedded segment headwinds
A9: AMD | B9: Advanced Micro Devices | C9: Q1 FY2025 | D9: 05/06/2025 | E9: 4 | F9: 4 | G9: 2 | H9: 3 | I9: 3 | J9: 3 | K9: =ROUND('About This Plugin'!$D$6*E9+'About This Plugin'!$D$7*F9+'About This Plugin'!$D$8*G9+'About This Plugin'!$D$9*H9+'About This Plugin'!$D$10*I9+'About This Plugin'!$D$11*J9,2) -> 3.3 | L9: Outstanding start; enterprise adoption accelerating; record EPYC sales | M9: Tariff and regulatory headwinds present
A10: AMD | B10: Advanced Micro Devices | C10: Q2 FY2025 | D10: 08/05/2025 | E10: 4 | F10: 4 | G10: 1 | H10: 2 | I10: 4 | J10: 3 | K10: =ROUND('About This Plugin'!$D$6*E10+'About This Plugin'!$D$7*F10+'About This Plugin'!$D$8*G10+'About This Plugin'!$D$9*H10+'About This Plugin'!$D$10*I10+'About This Plugin'!$D$11*J10,2) -> 3.05 | L10: Beat guidance; record CPU sales; export headwinds offset by strength | M10: Export control impacts on Instinct sales
A11: AMD | B11: Advanced Micro Devices | C11: Q3 FY2025 | D11: 11/04/2025 | E11: 4 | F11: 4 | G11: 2 | H11: 3 | I11: 4 | J11: 3 | K11: =ROUND('About This Plugin'!$D$6*E11+'About This Plugin'!$D$7*F11+'About This Plugin'!$D$8*G11+'About This Plugin'!$D$9*H11+'About This Plugin'!$D$10*I11+'About This Plugin'!$D$11*J11,2) -> 3.4 | L11: Record revenue and profitability; strong cloud demand; tens of billions AI revenue roadmap | M11: Minimal bearish signals
A12: AMD | B12: Advanced Micro Devices | C12: Q4 FY2025 | D12: 02/03/2026 | E12: 4 | F12: 4 | G12: 2 | H12: 3 | I12: 5 | J12: 3 | K12: =ROUND('About This Plugin'!$D$6*E12+'About This Plugin'!$D$7*F12+'About This Plugin'!$D$8*G12+'About This Plugin'!$D$9*H12+'About This Plugin'!$D$10*I12+'About This Plugin'!$D$11*J12,2) -> 3.5 | L12: Record revenue $10.3B; AI revenue tens of billions by 2027 target | M12: Gaming semi-custom expected to decline significantly in 2026
A13: CAT | B13: Caterpillar Inc. | C13: Q4 FY2024 | D13: 01/30/2025 | E13: 4 | F13: 4 | G13: 0 | H13: -3 | I13: 2 | J13: 4 | K13: =ROUND('About This Plugin'!$D$6*E13+'About This Plugin'!$D$7*F13+'About This Plugin'!$D$8*G13+'About This Plugin'!$D$9*H13+'About This Plugin'!$D$10*I13+'About This Plugin'!$D$11*J13,2) -> 1.8 | L13: Strong execution in delivering another good year | M13: Challenging comparative to Q4 2023
A14: CAT | B14: Caterpillar Inc. | C14: Q1 FY2025 | D14: 04/30/2025 | E14: 3 | F14: 4 | G14: -2 | H14: -2 | I14: 2 | J14: 3 | K14: =ROUND('About This Plugin'!$D$6*E14+'About This Plugin'!$D$7*F14+'About This Plugin'!$D$8*G14+'About This Plugin'!$D$9*H14+'About This Plugin'!$D$10*I14+'About This Plugin'!$D$11*J14,2) -> 1.4 | L14: Delivered adjusted operating profit above expectations | M14: Headwind of tariffs; lower price realization
... A51: WMT | B51: Walmart Inc. | C51: Q1 FY2026 | D51: 05/16/2025 | E51: 4 | F51: 3 | G51: 4 | H51: 4 | I51: 3 | J51: 3 | K51: =ROUND('About This Plugin'!$D$6*E51+'About This Plugin'!$D$7*F51+'About This Plugin'!$D$8*G51+'About This Plugin'!$D$9*H51+'About This Plugin'!$D$10*I51+'About This Plugin'!$D$11*J51,2) -> 3.55 | L51: Highly confident management; record metrics; strong analyst support | M51: Minimal bearish signals
A52: Score Legend: –5 = Very Negative | –3 = Negative | 0 = Neutral | +3 = Positive | +5 = Very Positive
A54: * Composite updates automatically when you change 'Your Weight' on the About This Plugin tab. Scale: –5 = Very Negative ··· 0 = Neutral ··· +5 = Very Positive
A55: ≥ +3.0 Positive | B55: ≥ +1.0 Mild Positive | C55: ≥ –1.0 Neutral | D55: ≥ –3.0 Mild Negative
